kube_resource_report/__init__.py
kube_resource_report/__main__.py
kube_resource_report/aws-ec2-costs-monthly.csv
kube_resource_report/aws-ec2-spot-costs-monthly.csv
kube_resource_report/cluster_discovery.py
kube_resource_report/example_hooks.py
kube_resource_report/filters.py
kube_resource_report/gcp-costs-monthly.csv
kube_resource_report/histogram.py
kube_resource_report/ingressroute.py
kube_resource_report/main.py
kube_resource_report/metrics.py
kube_resource_report/output.py
kube_resource_report/pricing.py
kube_resource_report/query.py
kube_resource_report/recommender.py
kube_resource_report/report.py
kube_resource_report/routegroup.py
kube_resource_report/templates/application.html
kube_resource_report/templates/applications.html
kube_resource_report/templates/assets/all.js
kube_resource_report/templates/assets/anchor.min.js
kube_resource_report/templates/assets/bulma.min.css
kube_resource_report/templates/assets/favicon.png
kube_resource_report/templates/assets/favicon.svg
kube_resource_report/templates/assets/kube-resource-report.css
kube_resource_report/templates/assets/kube-resource-report.js
kube_resource_report/templates/assets/sortable-theme-minimal.css
kube_resource_report/templates/assets/sortable.min.js
kube_resource_report/templates/base.html
kube_resource_report/templates/cluster.html
kube_resource_report/templates/clusters.html
kube_resource_report/templates/elements.html
kube_resource_report/templates/index.html
kube_resource_report/templates/ingresses.html
kube_resource_report/templates/ingressroutes.html
kube_resource_report/templates/loading.html
kube_resource_report/templates/namespaces.html
kube_resource_report/templates/node.html
kube_resource_report/templates/nodes.html
kube_resource_report/templates/partials/extrahead.html
kube_resource_report/templates/partials/footer.html
kube_resource_report/templates/partials/navbar.html
kube_resource_report/templates/pods.html
kube_resource_report/templates/routegroups.html
kube_resource_report-21.2.1.dist-info/entry_points.txt
kube_resource_report-21.2.1.dist-info/LICENSE
kube_resource_report-21.2.1.dist-info/WHEEL
kube_resource_report-21.2.1.dist-info/METADATA
kube_resource_report-21.2.1.dist-info/RECORD
